{
  "$id": "/v1/schemas/credentials/verifiable-credential.json",
  "title": "Verifiable Credential",
  "description": "A Verifiable Credential",
  "type": "object",
  "properties": {
    "@context": {},
    "type": {},
    "name": {
      "type": "string",
      "example": "CMTR Credential"
    },
    "description": {
      "type": "string",
      "example": "CMTR Credential description"
    },
    "credentialSubject": {},
    "credentialStatus": {},
    "relatedLink": {},
    "id": {
      "type": "string",
      "example": "https://example.com/credentials/123"
    },
    "issuer": {},
    "issuanceDate": {
      "type": "string",
      "example": "2021-02-17T15:58:15+00:00"
    },
    "proof": {}
  },
  "required": ["id", "proof"],
  "additionalProperties": true
}
